django_cloudwatch_metrics/apps.py
django_cloudwatch_metrics/hashing.py
django_cloudwatch_metrics/management/__init__.py
django_cloudwatch_metrics/management/commands/__init__.py
django_cloudwatch_metrics/management/commands/increment.py
django_cloudwatch_metrics/management/commands/publish_metrics.py
django_cloudwatch_metrics/metrics.py
django_cloudwatch_metrics/migrations/0001_initial.py
django_cloudwatch_metrics/migrations/0002_alter_metricaggregation_id.py
django_cloudwatch_metrics/migrations/0003_auto_20230606_1148.py
django_cloudwatch_metrics/migrations/__init__.py
django_cloudwatch_metrics/models.py
django_cloudwatch_metrics/signals.py
django_cloudwatch_metrics-0.0.15.dist-info/METADATA
django_cloudwatch_metrics-0.0.15.dist-info/WHEEL
django_cloudwatch_metrics-0.0.15.dist-info/RECORD
