Metadata-Version: 2.1
Name: django-cloudwatch-metrics
Version: 0.0.15
Summary: Metric tracking in Django using caching and CloudWatch
License: MIT
Author: Bart Machielsen
Author-email: bartmachielsen@gmail.com
Requires-Python: >=3.6.2
Classifier: License :: OSI Approved :: MIT License
Classifier: Programming Language :: Python :: 3
Classifier: Programming Language :: Python :: 3.7
Classifier: Programming Language :: Python :: 3.8
Classifier: Programming Language :: Python :: 3.9
Classifier: Programming Language :: Python :: 3.10
Classifier: Programming Language :: Python :: 3.11
Classifier: Programming Language :: Python :: 3.12
Requires-Dist: boto3
Requires-Dist: django
